flask_validation/__init__.py
flask_validation/flask_validation.py
validation/__init__.py
validation/base.py
validation/errors.py
validation/rules.py
validation/validation.py
validation/validation_message.py
validation/validation_rule.py
validation_py-0.2.0.dist-info/LICENSE
validation_py-0.2.0.dist-info/METADATA
validation_py-0.2.0.dist-info/WHEEL
validation_py-0.2.0.dist-info/top_level.txt
validation_py-0.2.0.dist-info/RECORD
