Metadata-Version: 2.1
Name: validation-py
Version: 0.2.0
Summary: Validation
Home-page: https://github.com/jedymatt/validation-py
Author: Jedy Matt Tabasco
Author-email: jedymatt@gmail.com
License: MIT
Project-URL: Source, https://github.com/jedymatt/validation-py
Project-URL: Tracker, https://github.com/jedymatt/validation-py/issues
Keywords: validation,validator,flask
License-File: LICENSE
Provides-Extra: flask
Requires-Dist: flask <4.0.0,>=3.0.0 ; extra == 'flask'
